walldown/__init__.py
walldown/progress_bar.py
walldown/utils/__init__.py
walldown/utils/_wallpaperflare.py
wallpaper_downloader-0.0.2.dist-info/LICENSE
wallpaper_downloader-0.0.2.dist-info/METADATA
wallpaper_downloader-0.0.2.dist-info/WHEEL
wallpaper_downloader-0.0.2.dist-info/RECORD
